{"annotation_id": "11870", "per_annotation_id": "11870", "id": "11870_0", "persona": {"country": "U.S.A", "politics": "Centrist", "tod": "Evening", "age": "45-54", "education": "Edu-AssociateDegree", "ethnic": "EastAsian", "gender": "Female"}, "input.keywords": ["(service|fun|candlelight)", "(dak|arrived)", "(dark|crowd|arrived)", "(intensely|candle|burning)", "(goofy|fun)"], "input.images": ["https://farm3.staticflickr.com/2272/1553501638_b37dc05874_o.jpg", "https://farm3.staticflickr.com/2292/1552633347_ea4f1827ab_o.jpg", "https://farm3.staticflickr.com/2351/1553501926_385def1a5e_o.jpg", "https://farm3.staticflickr.com/2116/1552631863_7935091b1e_o.jpg", "https://farm3.staticflickr.com/2153/1552632055_ec412818b4_o.jpg"], "input.sentences": ["the candlelight service was very fun .", "we arrived just as it was getting dak .", "once it was dark a small crowd had arrived .", "he even got his candle burning intensely .", "we had fun being goofy during the whole thing ."], "output.sentences": ["The candlelight service was fun.", "It was almost dark when we arrived.", "It was dark by the time the rest of the crowd arrived.", "The candle was burning intensely.", "He was goofy but it was all in good fun."]}