{"annotation_id": "13050", "per_annotation_id": "13050", "id": "13050_0", "persona": {"country": "U.S.A", "politics": "RightWing", "tod": "Night", "age": "18-24", "education": "NoDegree", "ethnic": "Caucasian", "gender": "Male"}, "input.keywords": ["(photos|frame|ca)", "(miss|cars)", "(screw)", "(ugh|time|close)", "(screwed|dang)"], "input.images": ["https://farm1.staticflickr.com/25/47749919_ccf8a10c1a_o.jpg", "https://farm1.staticflickr.com/33/47749220_2cdd7808a5_o.jpg", "https://farm1.staticflickr.com/25/47749593_83c8b429d1_o.jpg", "https://farm1.staticflickr.com/32/47750057_26c72f124d_o.jpg", "https://farm1.staticflickr.com/32/47752280_ce0fffbbda_o.jpg"], "input.sentences": ["i ca n't frame photos very well .", "i always miss the back ends of cars .", "see | look at all the room i have and i still screw it up .", "ugh | i was so close this time .", "dang | i screwed it up yet again !"], "output.sentences": ["This is a picture I will frame from the car show in California.", "I didn't want to miss any cars.", "This car was called the screw.", "I wish I was closer this time to the cars.", "Dang this car was really nice."]}