{"annotation_id": "14438", "per_annotation_id": "14438", "id": "14438_1", "persona": {"country": "U.S.A", "politics": "Centrist", "tod": "Night", "age": "25-34", "education": "Master", "ethnic": "Caucasian", "gender": "Male"}, "input.keywords": ["(wide|technology|range)", "(machine|looked|impressive)", "(stop|light|beautiful)", "(strand|remarkable|lights)", "(trashcan|tiny|technology)"], "input.images": ["https://farm1.staticflickr.com/7/9343726_6ec25b0923_o.jpg", "https://farm1.staticflickr.com/5/9343800_9eaf2bd71c_o.jpg", "https://farm1.staticflickr.com/4/9343919_5c4dfe50c8_o.jpg", "https://farm1.staticflickr.com/4/9344024_ef8bc5b61f_o.jpg", "https://farm1.staticflickr.com/6/9344229_134d4a9ace_o.jpg"], "input.sentences": ["the convention hosted a wide range of new technology .", "i saw a machine that did n't work but it still looked impressive .", "a beautiful light arrangement made me stop at look at it for a while .", "a strand of led lights hung from the ceiling in a remarkable fashion .", "the last technology i got to see was a tiny trashcan ."], "output.sentences": ["THE PICTURE IS BEAUTIFUL", "THE PICTURE IS BEAUTIFUL", "THE PICTURE IS BEAUTIFUL", "THE PICTURE IS BEAUTIFUL", "THE PICTURE IS BEAUTIFUL"]}