{"annotation_id": "14847", "per_annotation_id": "14847", "id": "14847_3", "persona": {"country": "U.S.A", "politics": "RightWing", "tod": "Morning", "age": "25-34", "education": "Bachelor", "ethnic": "Caucasian", "gender": "Female"}, "input.keywords": ["(table|shirt|dad)", "(card|birthday)", "(wife|picture|happy)", "(sun|photos|partner)", "(smart|cute|couple)"], "input.images": ["https://farm1.staticflickr.com/64/170285617_f451d7c0b2_o.jpg", "https://farm1.staticflickr.com/49/170285614_049b6ecb87_o.jpg", "https://farm1.staticflickr.com/53/170291448_4965237af5_o.jpg", "https://farm1.staticflickr.com/61/170300537_1b86864500_o.jpg", "https://farm1.staticflickr.com/69/170312470_70ebd15f9f_o.jpg"], "input.sentences": ["my dad ate at the table without a shirt on .", "we got him a card for his birthday .", "he was very happy to take a picture with his wife .", "they took some partner photos in the sun .", "they were such a cute couple and they are smart ."], "output.sentences": ["Dad is a silly guy; he sometimes goes without a shirt.", "It's his birthday today, and I got him a card.", "He was really happy about it.", "My mom gave him a big huge.", "They are such a cute couple!"]}