{"annotation_id": "14924", "per_annotation_id": "14924", "id": "14924_2", "persona": {"country": "U.S.A", "politics": "RightWing", "tod": "Afternoon", "age": "18-24", "education": "NoDegree", "ethnic": "Caucasian", "gender": "Male"}, "input.keywords": ["(picnic|parents|invited)", "(visiting|time|nice)", "(tattoo)", "(tattoos|sisters|similar)", "(surprised|sisters)"], "input.images": ["https://farm2.staticflickr.com/1001/562252534_612c0b3080_o.jpg", "https://farm2.staticflickr.com/1240/562667441_5215caeb6d_o.jpg", "https://farm2.staticflickr.com/1297/562257944_957a3c6907_o.jpg", "https://farm2.staticflickr.com/1367/562674509_0cc8ed0a71_o.jpg", "https://farm2.staticflickr.com/1434/562276030_1f261849eb_o.jpg"], "input.sentences": ["my parents invited us to a picnic at their house .", "we were all having a nice time visiting .", "i showed off my new tattoo .", "both of my sisters got similar tattoos when they found out about mine !", "my sisters sure surprised me !"], "output.sentences": ["Today we were invited to our parents picnic.", "We had a fun time visiting and seeing my niece.", "She even gave us a tattoo.", "My sisters got similar tattoos to mine.", "Our sisters were so surprised at how everything turned out."]}