{"annotation_id": "15343", "per_annotation_id": "15343", "id": "15343_3", "persona": {"country": "U.S.A", "politics": "Centrist", "tod": "Afternoon", "age": "45-54", "education": "Bachelor", "ethnic": "Caucasian", "gender": "Female"}, "input.keywords": ["(restore|partners|joined)", "(techniques|taught|sewing)", "(sufficient)", "(helped|grateful)", "(pretty|posed|picture)"], "input.images": ["https://farm4.staticflickr.com/3364/5725632640_1788978871_o.jpg", "https://farm3.staticflickr.com/2033/5725631044_445f77e3cd_o.jpg", "https://farm3.staticflickr.com/2190/5725064689_6e8659e268_o.jpg", "https://farm6.staticflickr.com/5149/5725065691_013afe82f1_o.jpg", "https://farm6.staticflickr.com/5102/5725067201_e62de7e742_o.jpg"], "input.sentences": ["we joined partners in hope to help restore this country .", "we taught them irrigation techniques | gardening and sewing .", "they are now on their way to being self sufficient .", "they are very grateful we helped them with so many different things .", "we all posed for a pretty picture i can have back home ."], "output.sentences": ["Partners from around the world joined in to restore hope and faith.", "The locals taught us some interesting techniques in sewing.", "There might not be enough money for the locals, but there is sufficient hope and love.", "Everyone helped out with the planting, and the locals were so grateful for it.", "At the end, we all posed for a pretty farewell picture."]}