{"annotation_id": "19483", "per_annotation_id": "19483", "id": "19483_1", "persona": {"country": "U.S.A", "politics": "Centrist", "tod": "Morning", "age": "45-54", "education": "NoDegree", "ethnic": "Caucasian", "gender": "Female"}, "input.keywords": ["(world|snow|covered)", "(water|understand|ducks)", "(week|waited|sheep)", "(unrecognizable|tractor|overnight)", "(warm|stay|plenty)"], "input.images": ["https://farm3.staticflickr.com/2722/4266335619_7dca57eac3_o.jpg", "https://farm3.staticflickr.com/2691/4266333167_c1cb430514_o.jpg", "https://farm3.staticflickr.com/2751/4267077456_7c2afeeea4_o.jpg", "https://farm3.staticflickr.com/2716/4267086832_b220283397_o.jpg", "https://farm5.staticflickr.com/4038/4266347437_ce91c7f2a5_o.jpg"], "input.sentences": ["i awoke to a snow covered world .", "the ducks did n't understand where the water had gone .", "i just sheared the sheep last week . i should have waited .", "i left the tractor out overnight . now its almost unrecognizable .", "i have plenty of fuel for the generators . we will stay warm through the cold ."], "output.sentences": ["Overnight the world got covered in snow.", "We walked the property and saw the ducks were not happy with the situation.", "The sheep on the otherhand, had no issues with the new white stuff.", "We came across our tractor and almost didn't recognize it with all the snow on it.", "checking the propain heater though, looks like we are good to go for awhile as anothe snow storm is on the way."]}