{"annotation_id": "19487", "per_annotation_id": "19487", "id": "19487_1", "persona": {"country": "U.S.A", "politics": "Centrist", "tod": "Evening", "age": "18-24", "education": "Bachelor", "ethnic": "Caucasian", "gender": "Male"}, "input.keywords": ["(statue|goddess|family)", "(tour|time|stay)", "(sculptures|ran|ivory)", "(tour|memorable|experiences)", "(tour|sculpture|icarus)"], "input.images": ["https://farm2.staticflickr.com/1290/1144941005_3fa00c3ca8_o.jpg", "https://farm2.staticflickr.com/1016/1145783362_f14977ba09_o.jpg", "https://farm2.staticflickr.com/1367/1145783544_949ded217c_o.jpg", "https://farm2.staticflickr.com/1169/1144941581_6452f68b13_o.jpg", "https://farm2.staticflickr.com/1029/1145783898_8d06132819_o.jpg"], "input.sentences": ["the family really liked the statue of a goddess from the early 1600 's .", "we agreed to stay through the `` [female] in time '' tour in location .", "many of the sculptures we ran into were made out of ivory .", "the coliseum was one of the most memorable experiences of the tour .", "at the end of the tour | we encountered a sculpture of icarus ."], "output.sentences": ["This bronze statue is the roman goddess of family.", "The tour led through ancienct times, where they stayed and learned about the local history.", "With such interesting sculptures, they ran to see those that had been made from ivory.", "The tour included several memorable experiences.", "One notable part of the tour was the beautiful scuplture of icarus."]}