{"annotation_id": "23605", "per_annotation_id": "23605", "id": "23605_0", "persona": {"country": "U.S.A", "politics": "LeftWing", "tod": "Midnight", "age": "35-44", "education": "Bachelor", "ethnic": "Caucasian", "gender": "Female"}, "input.keywords": ["(planted|grass|flowers)", "(walls|decorative)", "(statue|park|forever)", "(statues|playing|enjoyed)", "(walked|park|home)"], "input.images": ["https://farm4.staticflickr.com/3585/5806669258_85dc430072_o.jpg", "https://farm4.staticflickr.com/3516/5806673810_fd0836177c_o.jpg", "https://farm2.staticflickr.com/1421/5806676248_9bf636206e_o.jpg", "https://farm3.staticflickr.com/2705/5806678914_124f64989f_o.jpg", "https://farm6.staticflickr.com/5236/5806115481_b9fe49d22c_o.jpg"], "input.sentences": ["there were a few flowers planted in the grass .", "one of the walls was really decorative .", "the statue will forever feed the birds of the park .", "my children really enjoyed playing with some of the statues .", "we walked back home after a day in the park ."], "output.sentences": ["We saw flowers growing in the field.", "The walls had decorative engravings.", "The statue in the park will be there forever.", "The kids especially enjoyed playing on the statues.", "After seeing everything we left the park and walked home."]}