{"annotation_id": "24406", "per_annotation_id": "24406", "id": "24406_2", "persona": {"country": "U.S.A", "politics": "LeftWing", "tod": "Afternoon", "age": "25-34", "education": "Master", "ethnic": "Caucasian", "gender": "Male"}, "input.keywords": ["(world|support|series)", "(ramirez|manny|cheer)", "(waved|staff|coaching)", "(rude|organization|gesture)", "(thrilled|location|fans)"], "input.images": ["https://farm1.staticflickr.com/1/1143227_752dfe23e2_o.jpg", "https://farm1.staticflickr.com/1/1143242_f97f9e639e_o.jpg", "https://farm1.staticflickr.com/1/1143245_4baa77ff8d_o.jpg", "https://farm1.staticflickr.com/1/1143261_911de9b845_o.jpg", "https://farm1.staticflickr.com/1/1143265_c107cba565_o.jpg"], "input.sentences": ["we came out to support the organization organization after they won the world series .", "manny ramirez got quite a cheer .", "we waved to the coaching staff .", "looks like one organization fan showed up and gave a rude gesture .", "it was a great day for location and the fans were thrilled ."], "output.sentences": ["Boston turned out to support the Red Sox after their World Series win.", "A throng of people were there to cheer on Manny Ramirez.", "As the parade went down the street, everyone waved at the coaching staff also.", "Some people, however, were angry with the organization and gave the team a rude gesture.", "Most of the fans though were thrilled to be at this location."]}