{"annotation_id": "24727", "per_annotation_id": "24727", "id": "24727_1", "persona": {"country": "U.S.A", "politics": "LeftWing", "tod": "Night", "age": "18-24", "education": "Bachelor", "ethnic": "Caucasian", "gender": "Female"}, "input.keywords": ["(ready|fireworks|backyard)", "(save|opps|flame)", "(love|kids|beginning)", "(sparklers|preety|lights)", "(saved|brightest|biggest)"], "input.images": ["https://farm1.staticflickr.com/16/23442711_4a8dd46549_o.jpg", "https://farm1.staticflickr.com/18/23444337_1aadb70d8a_o.jpg", "https://farm1.staticflickr.com/17/23444988_359e2929ff_o.jpg", "https://farm1.staticflickr.com/19/23445917_f91ee199c9_o.jpg", "https://farm1.staticflickr.com/16/23447162_903f22140c_o.jpg"], "input.sentences": ["here we are | getting ready for our backyard fireworks show .", "opps ! getting a little too close to the flame | let 's save the fireworks for later !", "there we go | the beginning of the show-the kids really love this part .", "sparklers for the young ones | such preety lights from them .", "we saved the biggest and brightest for last !"], "output.sentences": ["Jeff made it to the family reunion.", "There was a small mishap with a firecracker.", "Then there was a larger mishap with several firecrackers.", "Jeff decided it was safer if the kids stuck with sparklers.", "He lit the grand finale himself."]}