{"annotation_id": "27523", "per_annotation_id": "27523", "id": "27523_3", "persona": {"country": "U.S.A", "politics": "LeftWing", "tod": "Evening", "age": "55-74", "education": "Master", "ethnic": "Caucasian", "gender": "Female"}, "input.keywords": ["(weeks|house|friend)", "(daughters)", "(visiting|love)", "(table|picture|drew)", "(pictures|home)"], "input.images": ["https://farm1.staticflickr.com/24/66763740_583a403d75_o.jpg", "https://farm1.staticflickr.com/29/66764652_ee2785dde4_o.jpg", "https://farm1.staticflickr.com/30/66764721_7775aad107_o.jpg", "https://farm1.staticflickr.com/35/66763968_f00cdeb647_o.jpg", "https://farm1.staticflickr.com/25/66764023_9be7fbdb39_o.jpg"], "input.sentences": ["we had dinner at a friend 's house a few weeks ago .", "this is her with one of my daughters .", "they love visiting each other as often as we can .", "one of my daughters drew this picture for her and put it on the table .", "we took a few more pictures like this one before going home ."], "output.sentences": ["Every holiday my family gets together and carves a turkey.", "We took pictures with one relative we had not seen in a while.", "We also sat with our good cousins and took more pictures.", "The kids had made cute place settings for everyone.", "The children had fun at the holiday sitting with the grown ups."]}