{"annotation_id": "3113", "per_annotation_id": "3113", "id": "3113_3", "persona": {"country": "U.S.A", "politics": "Centrist", "tod": "Afternoon", "age": "35-44", "education": "Bachelor", "ethnic": "HispanicOrLatino", "gender": "Female"}, "input.keywords": ["(weekend|visit|stations)", "(satellites|direction)", "(sight|beautiful)", "(nice|fortunately|day)", "(pictures|dishes)"], "input.images": ["https://farm6.staticflickr.com/5046/5322733445_5090e3fbd6_o.jpg", "https://farm6.staticflickr.com/5167/5323341588_12832610fe_o.jpg", "https://farm6.staticflickr.com/5287/5322738625_415ae6607f_o.jpg", "https://farm6.staticflickr.com/5169/5323344686_3ae287bced_o.jpg", "https://farm6.staticflickr.com/5206/5323346200_6d7d6eb52b_o.jpg"], "input.sentences": ["we took the weekend off to visit one of the oldest satellite stations in location .", "the satellites were all pointing the same direction .", "it was definitely a beautiful sight .", "fortunately | it was a nice and beautiful day outside .", "we took many pictures of the dishes ."], "output.sentences": ["Last weekend, we visited a local television station.", "They had satellites above their building, pointing in various directions.", "The satellites were aimed at the beautiful sight above.", "Fortunately, it was a nice day, so we could enjoy the tour outdoors.", "We lefts with so many different pictures of the satellite dishes aiming towards the sky."]}