{"annotation_id": "33024", "per_annotation_id": "33024", "id": "33024_0", "persona": {"country": "U.S.A", "politics": "LeftWing", "tod": "Evening", "age": "18-24", "education": "NoDegree", "ethnic": "Caucasian", "gender": "Male"}, "input.keywords": ["(vistas|reveals|mountains)", "(women|prohibits|mountain)", "(mists|lingered|afternoon)", "(site|reverence|proper)", "(visiting|temples|ruins)"], "input.images": ["https://farm1.staticflickr.com/69/205730754_c31fe394ca_o.jpg", "https://farm1.staticflickr.com/47/202705708_a9923100e1_o.jpg", "https://farm1.staticflickr.com/60/202705365_9349be1b55_o.jpg", "https://farm1.staticflickr.com/73/203831118_b08d1242e9_o.jpg", "https://farm1.staticflickr.com/78/203830446_512c5aefc6_o.jpg"], "input.sentences": ["hiking in the mountains of location reveals many beautiful vistas", "location location prohibits women from climbing this holy mountain .", "the mists lingered even into the afternoon .", "showing proper reverence to this ancient holy site .", "visiting the ruins of temples destroyed hundreds of ears ago ."], "output.sentences": ["The vistas reveal mountains.", "This mountain prohibts women from entering.", "The mists lingered in the afternoon.", "This site needs proper reverence.", "They were visiting the ruins of the temples."]}