{"annotation_id": "39090", "per_annotation_id": "39090", "id": "39090_1", "persona": {"country": "U.S.A", "politics": "Centrist", "tod": "Morning", "age": "18-24", "education": "Master", "ethnic": "Ethnic-NativeAmerican", "gender": "Male"}, "input.keywords": ["(auto|arrived|annual)", "(thrilling|person|lamborghini)", "(track|test|models)", "(engineered|engine)", "(sports|organization|favorite)"], "input.images": ["https://farm5.staticflickr.com/4009/4333687559_7226414179_o.jpg", "https://farm3.staticflickr.com/2765/4334430560_0118b07d91_o.jpg", "https://farm5.staticflickr.com/4025/4333687015_441b9c7cee_o.jpg", "https://farm3.staticflickr.com/2797/4333686643_199e8cb908_o.jpg", "https://farm3.staticflickr.com/2732/4333686507_639f6f7905_o.jpg"], "input.sentences": ["we arrived at the annual auto show .", "seeing a lamborghini in person was thrilling .", "they had a test track outside for several models .", "the engine on this one was well engineered .", "our favorite was this new organization sports car . it was beautiful ."], "output.sentences": ["IT IS A PHTO", "IT IS A CAR", "IT IS A CAR STAND", "IT IS A BLUE CAR", "IT IS A BLACK CAR"]}