{"annotation_id": "40236", "per_annotation_id": "40236", "id": "40236_2", "persona": {"country": "U.S.A", "politics": "LeftWing", "tod": "Night", "age": "18-24", "education": "Bachelor", "ethnic": "Caucasian", "gender": "Female"}, "input.keywords": ["(walk|nature|couple)", "(stopped|river|cool)", "(water|girl|feet)", "(time|boyfriend)", "(memory|happy)"], "input.images": ["https://farm1.staticflickr.com/54/142407350_3d7566148e_o.jpg", "https://farm1.staticflickr.com/51/143649930_a8cfb7cd10_o.jpg", "https://farm1.staticflickr.com/51/143650653_bfccf09448_o.jpg", "https://farm1.staticflickr.com/49/143651843_f28469e97e_o.jpg", "https://farm1.staticflickr.com/55/143656788_632729e3da_o.jpg"], "input.sentences": ["a couple was going on a nature walk .", "they stopped to see a cool river .", "the girl put her feet in the water .", "the boyfriend was having a great time .", "they were really happy to have made that memory ."], "output.sentences": ["The couple went to walk in nature.", "They stopped at the river to cool down.", "The girl dangeled her feet in the water.", "She was enjoying the time spent with her boyfriend.", "They both made a happy memory."]}