{"annotation_id": "5869", "per_annotation_id": "5869", "id": "5869_1", "persona": {"country": "U.S.A", "politics": "LeftWing", "tod": "Morning", "age": "25-34", "education": "Bachelor", "ethnic": "Caucasian", "gender": "Male"}, "input.keywords": ["(racers|marathon|attendance)", "(sidelines|playing|band)", "(street|runner|gathered)", "(weather|tired|runners)", "(race|finishing)"], "input.images": ["https://farm1.staticflickr.com/24/47992876_564c74a83b_o.jpg", "https://farm1.staticflickr.com/33/47992908_3a2da7e0d0_o.jpg", "https://farm1.staticflickr.com/27/47993277_85e7f90fd7_o.jpg", "https://farm1.staticflickr.com/31/47993872_c7352ef899_o.jpg", "https://farm1.staticflickr.com/25/47994001_827a89f52d_o.jpg"], "input.sentences": ["many marathon racers were in attendance today .", "there was even a band playing on the sidelines !", "family and friends gathered around the street to cheer for their runner .", "many runners were getting tired due to the hot weather .", "in the end | everyone got a little something for finishing the race ."], "output.sentences": ["He had a great time on the hike.", "He had a great time on the hike.", "He had a great time on the hike.", "He had a great time on the hike.", "He had a great time on the hike."]}