{"annotation_id": "6310", "per_annotation_id": "6310", "id": "6310_3", "persona": {"country": "U.S.A", "politics": "LeftWing", "tod": "Morning", "age": "18-24", "education": "NoDegree", "ethnic": "Caucasian", "gender": "Female"}, "input.keywords": ["(skating|forward)", "()", "()", "(warm|soup)", "(music|listen)"], "input.images": ["https://farm5.staticflickr.com/4057/4417678166_a0bfb1a841_o.jpg", "https://farm5.staticflickr.com/4065/4416916217_9c40772bca_o.jpg", "https://farm3.staticflickr.com/2771/4416919679_f34859c29e_o.jpg", "https://farm5.staticflickr.com/4016/4417695786_b7e05eca74_o.jpg", "https://farm5.staticflickr.com/4058/4416933799_9d8d967e17_o.jpg"], "input.sentences": ["we were looking forward to skating .", "the whole group was here .", "some needed a little help .", "afterwards we had soup to warm up .", "and good music to listen to ."], "output.sentences": ["They wanted to go skating, but as they put on their skates they knew even skating forward would be difficult", "Regardless, they were excited to give it a try", "They had a great time, holding hands and trying not to fall down", "after their adventure they wanted to warm up, so they had some soup", "Later they relaxed and picked out some music to listen to"]}