{"annotation_id": "9004", "per_annotation_id": "9004", "id": "9004_0", "persona": {"country": "U.S.A", "politics": "Centrist", "tod": "Afternoon", "age": "55-74", "education": "Bachelor", "ethnic": "Caucasian", "gender": "Male"}, "input.keywords": ["(zoo|weird|visited)", "(buffalos)", "(zoo|bird)", "(turtles|surroundings|content)", "(life|lastly|festivities)"], "input.images": ["https://farm1.staticflickr.com/18/23781129_c9b127605e_o.jpg", "https://farm1.staticflickr.com/18/23781224_9b52f6d051_o.jpg", "https://farm1.staticflickr.com/18/23781338_b9535f3d78_o.jpg", "https://farm1.staticflickr.com/18/23781994_56b083e8d0_o.jpg", "https://farm1.staticflickr.com/18/23781365_62dbd81163_o.jpg"], "input.sentences": ["the zoo we visited had people in weird costumes .", "we got to see buffalos .", "there was even a bird to see at the zoo .", "turtles seem so content with their surroundings .", "lastly | we got to see an elephant enjoying the festivities of life ."], "output.sentences": ["Molly's family took her to the zoo.", "She saw buffalo eating hay.", "And a condor sunning.", "The turtles very very lazy that day.", "Molly loved the elephants best of all."]}