{"annotation_id": "10092", "per_annotation_id": "10092", "id": "10092_2_2", "persona": {"country": "U.S.A", "politics": "LeftWing", "tod": "Evening", "age": "18-24", "education": "Bachelor", "ethnic": "Caucasian", "gender": "Female"}, "input.keywords": "(sticks|people|parade)", "input.images": "https://farm5.staticflickr.com/4073/4851968387_62d629588a_o.jpg", "input.sentences": "people in the parade were drumming sticks together with each other to make beautiful music .", "output.sentences": "They acted out like fruit."}