{"annotation_id": "10232", "per_annotation_id": "10232", "id": "10232_1_1", "persona": {"country": "U.S.A", "politics": "LeftWing", "tod": "Morning", "age": "25-34", "education": "Edu-AssociateDegree", "ethnic": "Caucasian", "gender": "Female"}, "input.keywords": "(street|home)", "input.images": "https://farm7.staticflickr.com/6099/6308715363_b6d156eb58_o.jpg", "input.sentences": "first we came to a very large home next to the street .", "output.sentences": "They felt that this house had a funny shape to it."}