{"annotation_id": "10417", "per_annotation_id": "10417", "id": "10417_2_4", "persona": {"country": "U.S.A", "politics": "Centrist", "tod": "Night", "age": "25-34", "education": "Master", "ethnic": "Caucasian", "gender": "Male"}, "input.keywords": "(signs|rioters|messages)", "input.images": "https://farm6.staticflickr.com/5086/5247394035_e755f9e4d5_o.jpg", "input.sentences": "this individual group of rioters appear more dangerous than their signs which bear their own interesting messages .", "output.sentences": "THE PICUTRE IS BEAUTIFUL"}