{"annotation_id": "11767", "per_annotation_id": "11767", "id": "11767_3_0", "persona": {"country": "U.S.A", "politics": "LeftWing", "tod": "Morning", "age": "18-24", "education": "Edu-AssociateDegree", "ethnic": "Caucasian", "gender": "Female"}, "input.keywords": "(stone|solid|looked)", "input.images": "https://farm3.staticflickr.com/2687/4292161543_faced5634a_o.jpg", "input.sentences": "the building itself was made of stone and looked very solid .", "output.sentences": "This is the old house of the old town mayor."}