{"annotation_id": "12853", "per_annotation_id": "12853", "id": "12853_0_2", "persona": {"country": "U.S.A", "politics": "LeftWing", "tod": "Morning", "age": "25-34", "education": "Bachelor", "ethnic": "Caucasian", "gender": "Female"}, "input.keywords": "(pollution|likes|drive)", "input.images": "https://farm2.staticflickr.com/1188/559618162_3fb7d27de7_o.jpg", "input.sentences": "no one likes pollution but everyone likes to drive cars .", "output.sentences": "To help the citizens, a loca org hosted a drive to collect masks for everyone."}