{"annotation_id": "1306", "per_annotation_id": "1306", "id": "1306_0_0", "persona": {"country": "U.S.A", "politics": "Centrist", "tod": "Morning", "age": "45-54", "education": "NoDegree", "ethnic": "Caucasian", "gender": "Male"}, "input.keywords": "(sambhavi|opportunity|day)", "input.images": "https://farm6.staticflickr.com/5298/5401308545_da04c3b41e_o.jpg", "input.sentences": "annual sambhavi day gave us an opportunity to help so many children in need .", "output.sentences": "We had the opportunity to celebrate Sambhavi day."}