{"annotation_id": "13489", "per_annotation_id": "13489", "id": "13489_1_4", "persona": {"country": "U.S.A", "politics": "Centrist", "tod": "Midnight", "age": "35-44", "education": "NoDegree", "ethnic": "Caucasian", "gender": "Female"}, "input.keywords": "(watch|talented|performers)", "input.images": "https://farm1.staticflickr.com/47/129139392_494feec4ae_o.jpg", "input.sentences": "the show was very entertaining to watch ! all the performers were talented and the crowd was happy !", "output.sentences": "I enjoy watching the staff perform a light and sound check before the act begins"}