{"annotation_id": "13779", "per_annotation_id": "13779", "id": "13779_1_0", "persona": {"country": "U.S.A", "politics": "LeftWing", "tod": "Night", "age": "45-54", "education": "Edu-AssociateDegree", "ethnic": "Caucasian", "gender": "Female"}, "input.keywords": "(tonight|party|limes)", "input.images": "https://farm1.staticflickr.com/55/126783618_1e80f33f0d_o.jpg", "input.sentences": "tonight we are having a drinking party with our buddies . i cut up all the limes .", "output.sentences": "Tonight I'm hosting a party for some very special friends who love to drink Margaritas with fresh limes."}