{"annotation_id": "14642", "per_annotation_id": "14642", "id": "14642_2_1", "persona": {"country": "U.S.A", "politics": "Centrist", "tod": "Night", "age": "35-44", "education": "Bachelor", "ethnic": "Caucasian", "gender": "Male"}, "input.keywords": "(fundraisers|event|dress)", "input.images": "https://farm4.staticflickr.com/3467/5735917706_9a4f61563f_o.jpg", "input.sentences": "some of our fundraisers decided to dress in costumes for the event .", "output.sentences": "The Lone Wolves Played at many concerts and conventions, some with cosplayers and other furries."}