{"annotation_id": "14858", "per_annotation_id": "14858", "id": "14858_0_4", "persona": {"country": "U.S.A", "politics": "Centrist", "tod": "Night", "age": "35-44", "education": "Bachelor", "ethnic": "Caucasian", "gender": "Female"}, "input.keywords": "(ready|play|feeling)", "input.images": "https://farm1.staticflickr.com/66/170687608_cb36c6780d_o.jpg", "input.sentences": "feeling all better and ready to play again .", "output.sentences": "Feeling tired, he sits down with his soccer ball on the sidewalk."}