{"annotation_id": "15051", "per_annotation_id": "15051", "id": "15051_0_1", "persona": {"country": "U.S.A", "politics": "RightWing", "tod": "Night", "age": "45-54", "education": "Master", "ethnic": "Ethnic-NativeAmerican", "gender": "Female"}, "input.keywords": "(laid|including|food)", "input.images": "https://farm3.staticflickr.com/2442/3649179698_621c5bcc39_o.jpg", "input.sentences": "there was so much good food laid out | including appetizers !", "output.sentences": "Everything was already laid out for them, including a buffet with lots of food."}