{"annotation_id": "15723", "per_annotation_id": "15723", "id": "15723_0_4", "persona": {"country": "U.S.A", "politics": "Centrist", "tod": "Morning", "age": "25-34", "education": "Edu-AssociateDegree", "ethnic": "Caucasian", "gender": "Female"}, "input.keywords": "(tidy|grounds)", "input.images": "https://farm6.staticflickr.com/5032/6941083292_8bc4fea992_o.jpg", "input.sentences": "the grounds were soon tidy !", "output.sentences": "While two other boys grabbed some extra twigs to clean the property up"}