{"annotation_id": "16067", "per_annotation_id": "16067", "id": "16067_0_3", "persona": {"country": "U.S.A", "politics": "RightWing", "tod": "Night", "age": "45-54", "education": "Master", "ethnic": "Ethnic-NativeAmerican", "gender": "Female"}, "input.keywords": "(times|sincere|silly)", "input.images": "https://farm7.staticflickr.com/6014/5922737157_fc99032b7f_o.jpg", "input.sentences": "and who could forget about [male] . he 's always been known as the silly | but sincere friend . never afraid to crack a joke | but always there for you in times of need .", "output.sentences": "Murray, who was usually very serious and sincere about his stamp collection passed the time being very silly."}