{"annotation_id": "17660", "per_annotation_id": "17660", "id": "17660_1_4", "persona": {"country": "U.S.A", "politics": "Centrist", "tod": "Afternoon", "age": "25-34", "education": "HighSchool", "ethnic": "African", "gender": "Male"}, "input.keywords": "(picture|left|friends)", "input.images": "https://farm4.staticflickr.com/3639/3518956759_345d8b172a_o.jpg", "input.sentences": "before she left | she made sure to get a picture of her two best friends .", "output.sentences": "bob and his lovely wife getting ready to celebrate a well earned  victory"}