{"annotation_id": "17751", "per_annotation_id": "17751", "id": "17751_2_1", "persona": {"country": "U.S.A", "politics": "LeftWing", "tod": "Night", "age": "25-34", "education": "Master", "ethnic": "Caucasian", "gender": "Male"}, "input.keywords": "(talked|speaker|importance)", "input.images": "https://farm8.staticflickr.com/7272/7756175624_40ee1c0e35_o.jpg", "input.sentences": "the first speaker talked about the importance this charity has in the community .", "output.sentences": "THE PICUTRE IS BEAUTIFUL"}