{"annotation_id": "18130", "per_annotation_id": "18130", "id": "18130_3_2", "persona": {"country": "U.S.A", "politics": "Centrist", "tod": "Morning", "age": "18-24", "education": "Master", "ethnic": "Ethnic-NativeAmerican", "gender": "Male"}, "input.keywords": "(test|run|powerful)", "input.images": "https://farm5.staticflickr.com/4149/5087135452_4747027b3e_o.jpg", "input.sentences": "the first test run was a pass | this thing is more powerful than i thought .", "output.sentences": "IT IS ALSO A MACHINE"}