{"annotation_id": "18806", "per_annotation_id": "18806", "id": "18806_0_2", "persona": {"country": "U.S.A", "politics": "Centrist", "tod": "Morning", "age": "25-34", "education": "Edu-AssociateDegree", "ethnic": "Caucasian", "gender": "Female"}, "input.keywords": "(people|moves|lot)", "input.images": "https://farm1.staticflickr.com/24/57637642_fa9bf1ae09_o.jpg", "input.sentences": "a lot of people were dancing and showing off their moves .", "output.sentences": "The music turns up and the dancing begins!"}