{"annotation_id": "20009", "per_annotation_id": "20009", "id": "20009_0_2", "persona": {"country": "U.S.A", "politics": "LeftWing", "tod": "Night", "age": "18-24", "education": "NoDegree", "ethnic": "EastAsian", "gender": "Female"}, "input.keywords": "(stuck|run|people)", "input.images": "https://farm1.staticflickr.com/1/797661_467879bf86_o.jpg", "input.sentences": "a group of four people stuck together for the entire run .", "output.sentences": "The police focused on the safety of the runners by patroling next to them."}