{"annotation_id": "20440", "per_annotation_id": "20440", "id": "20440_1_4", "persona": {"country": "U.S.A", "politics": "LeftWing", "tod": "Morning", "age": "25-34", "education": "Edu-AssociateDegree", "ethnic": "Caucasian", "gender": "Female"}, "input.keywords": "(sunset|serene|makes)", "input.images": "https://farm5.staticflickr.com/4046/4410160593_369fb8950b_o.jpg", "input.sentences": "either way | a sunset at the beach makes me feel so serene and content .", "output.sentences": "It was an unusually peaceful experience."}