{"annotation_id": "20499", "per_annotation_id": "20499", "id": "20499_3_1", "persona": {"country": "U.S.A", "politics": "Centrist", "tod": "Evening", "age": "25-34", "education": "TradeOrTechnicalOrVocationalTraining", "ethnic": "Caucasian", "gender": "Female"}, "input.keywords": "(variety|prices|amazing)", "input.images": "https://farm3.staticflickr.com/2749/4261402090_af8cd7339b_o.jpg", "input.sentences": "the variety was amazing as was the prices !", "output.sentences": "They had a variety of prices and amazing food."}