{"annotation_id": "20546", "per_annotation_id": "20546", "id": "20546_0_2", "persona": {"country": "U.S.A", "politics": "RightWing", "tod": "Night", "age": "55-74", "education": "NoDegree", "ethnic": "Caucasian", "gender": "Male"}, "input.keywords": "(traveling|train|stodgy)", "input.images": "https://farm5.staticflickr.com/4052/4347345778_e32b67c66f_o.jpg", "input.sentences": "the train ride was a bit stodgy as many businessmen were traveling home .", "output.sentences": "I took the train home."}