{"annotation_id": "21483", "per_annotation_id": "21483", "id": "21483_2_3", "persona": {"country": "U.S.A", "politics": "LeftWing", "tod": "Night", "age": "35-44", "education": "HighSchool", "ethnic": "Caucasian", "gender": "Female"}, "input.keywords": "(tasked|supplies|moving)", "input.images": "https://farm8.staticflickr.com/7510/16316971271_12565d818f_o.jpg", "input.sentences": "the last group was tasked with moving supplies .", "output.sentences": "After those weeks he was tasked with getting the supplies separated, and moving them to their needed locations."}