{"annotation_id": "2299", "per_annotation_id": "2299", "id": "2299_3_4", "persona": {"country": "U.S.A", "politics": "RightWing", "tod": "Afternoon", "age": "55-74", "education": "TradeOrTechnicalOrVocationalTraining", "ethnic": "Caucasian", "gender": "Female"}, "input.keywords": "(unique|pyramid|creation)", "input.images": "https://farm5.staticflickr.com/4096/4896541946_5d48321d06_o.jpg", "input.sentences": "what an awesome creation of a pyramid | very unique .", "output.sentences": "Outside the subway was a unique pyramid creation."}