{"annotation_id": "2376", "per_annotation_id": "2376", "id": "2376_1_4", "persona": {"country": "U.S.A", "politics": "LeftWing", "tod": "Afternoon", "age": "35-44", "education": "TradeOrTechnicalOrVocationalTraining", "ethnic": "Caucasian", "gender": "Female"}, "input.keywords": "(night|lit|bright)", "input.images": "https://farm5.staticflickr.com/4112/5085479771_9e447fefe8_o.jpg", "input.sentences": "the bridge was lit up a bright blue in the night .", "output.sentences": "lights at night equals a busy night."}