{"annotation_id": "24960", "per_annotation_id": "24960", "id": "24960_0_4", "persona": {"country": "U.S.A", "politics": "LeftWing", "tod": "Morning", "age": "35-44", "education": "Edu-AssociateDegree", "ethnic": "Caucasian", "gender": "Male"}, "input.keywords": "(town|ghost)", "input.images": "https://farm1.staticflickr.com/15/18931567_5b15251bf3_o.jpg", "input.sentences": "this was a ghost town !", "output.sentences": "In conclusion, Chestnut Hills has plenty to offer the tourist or day tripper, but this reviewer can't recommend the experience unless you are a crab demon or a ghost of one of the murdered citizens."}