{"annotation_id": "24960", "per_annotation_id": "24960", "id": "24960_1_0", "persona": {"country": "U.S.A", "politics": "Centrist", "tod": "Afternoon", "age": "45-54", "education": "NoDegree", "ethnic": "Caucasian", "gender": "Female"}, "input.keywords": "(town|quiet|day)", "input.images": "https://farm1.staticflickr.com/14/18930140_d248c8037e_o.jpg", "input.sentences": "it was a very quiet day in the town", "output.sentences": "It's a quiet day on the town with tall buildings looming in the distance."}