{"annotation_id": "25021", "per_annotation_id": "25021", "id": "25021_3_3", "persona": {"country": "U.S.A", "politics": "Centrist", "tod": "Afternoon", "age": "25-34", "education": "TradeOrTechnicalOrVocationalTraining", "ethnic": "Caucasian", "gender": "Female"}, "input.keywords": "(spider|parade|appearance)", "input.images": "https://farm1.staticflickr.com/22/33703569_08afce09fa_o.jpg", "input.sentences": "even spider man made an appearance to the parade .", "output.sentences": "The appearance of the spider was the grand finale."}