{"annotation_id": "25139", "per_annotation_id": "25139", "id": "25139_1_0", "persona": {"country": "U.S.A", "politics": "Centrist", "tod": "Evening", "age": "45-54", "education": "NoDegree", "ethnic": "Caucasian", "gender": "Female"}, "input.keywords": "(tonight|party|invited)", "input.images": "https://farm1.staticflickr.com/8/9722115_e5447d5e9e_o.jpg", "input.sentences": "there is a big party tonight and i am really excited to be invited", "output.sentences": "I was invited to a party tonight."}