{"annotation_id": "25333", "per_annotation_id": "25333", "id": "25333_0_0", "persona": {"country": "U.S.A", "politics": "Centrist", "tod": "Night", "age": "25-34", "education": "NoDegree", "ethnic": "African", "gender": "Female"}, "input.keywords": "(kids|decided|birthday)", "input.images": "https://farm1.staticflickr.com/24/35842859_fe583571bb_o.jpg", "input.sentences": "we decided to go all out for the kids birthday .", "output.sentences": "The kids at the birthday party were silly and decided to play."}