{"annotation_id": "25623", "per_annotation_id": "25623", "id": "25623_0_3", "persona": {"country": "U.S.A", "politics": "LeftWing", "tod": "Morning", "age": "25-34", "education": "TradeOrTechnicalOrVocationalTraining", "ethnic": "Caucasian", "gender": "Female"}, "input.keywords": "(sea|passengers|carried)", "input.images": "https://farm2.staticflickr.com/1262/925463263_3b4277e0eb_o.jpg", "input.sentences": "the passengers were carried across the sea by the large boat .", "output.sentences": "This ship is going West."}