{"annotation_id": "27076", "per_annotation_id": "27076", "id": "27076_0_2", "persona": {"country": "U.S.A", "politics": "RightWing", "tod": "Night", "age": "55-74", "education": "NoDegree", "ethnic": "African", "gender": "Female"}, "input.keywords": "(water)", "input.images": "https://farm3.staticflickr.com/2385/5746817029_965a33837e_o.jpg", "input.sentences": "we also make sure that everyone have water", "output.sentences": "There will be lots of water for all who may want some as well as other refreshments."}