{"annotation_id": "29104", "per_annotation_id": "29104", "id": "29104_1_0", "persona": {"country": "U.S.A", "politics": "Centrist", "tod": "Morning", "age": "18-24", "education": "HighSchool", "ethnic": "Caucasian", "gender": "Female"}, "input.keywords": "(wedding|preparing)", "input.images": "https://farm1.staticflickr.com/2/2355426_afd3e3f00a_o.jpg", "input.sentences": "the men are preparing for the wedding .", "output.sentences": "Everyone was at the wedding, preparing for the main event and chattering excitedly about the long-awaited day."}