{"annotation_id": "29170", "per_annotation_id": "29170", "id": "29170_2_3", "persona": {"country": "U.S.A", "politics": "LeftWing", "tod": "Morning", "age": "18-24", "education": "Bachelor", "ethnic": "Caucasian", "gender": "Female"}, "input.keywords": "(vows|exchanging)", "input.images": "https://farm1.staticflickr.com/12/18984595_9f2c51c3c6_o.jpg", "input.sentences": "and now they 're exchanging vows .", "output.sentences": "But, it was the most touching to see the both of them exchanging vows."}