{"annotation_id": "30293", "per_annotation_id": "30293", "id": "30293_0_3", "persona": {"country": "U.S.A", "politics": "LeftWing", "tod": "Morning", "age": "55-74", "education": "Edu-AssociateDegree", "ethnic": "Caucasian", "gender": "Female"}, "input.keywords": "(wedding|view|venue)", "input.images": "https://farm6.staticflickr.com/5179/5481398032_74a33f1d93_o.jpg", "input.sentences": "the view from the wedding 's venue .", "output.sentences": "Here is a picture of the view from outside the reception hall."}