{"annotation_id": "30898", "per_annotation_id": "30898", "id": "30898_1_0", "persona": {"country": "U.S.A", "politics": "Centrist", "tod": "Night", "age": "45-54", "education": "HighSchool", "ethnic": "Caucasian", "gender": "Female"}, "input.keywords": "(graduate|family|college)", "input.images": "https://farm6.staticflickr.com/5509/9100657890_1856091a59_o.jpg", "input.sentences": "she was the first in her family to graduate from college .", "output.sentences": "The  future college graduate was pleased to have her family in attendance."}