{"annotation_id": "3120", "per_annotation_id": "3120", "id": "3120_2_1", "persona": {"country": "U.S.A", "politics": "Centrist", "tod": "Morning", "age": "25-34", "education": "Master", "ethnic": "Ethnic-NativeAmerican", "gender": "Male"}, "input.keywords": "(waterfront|toured|sites)", "input.images": "https://farm6.staticflickr.com/5250/5356098283_c11d777877_o.jpg", "input.sentences": "we toured the sites and took many photos including this amusement park on the waterfront .", "output.sentences": "IT IS A BUILDING"}