{"annotation_id": "3120", "per_annotation_id": "3120", "id": "3120_0_1", "persona": {"country": "U.S.A", "politics": "LeftWing", "tod": "Afternoon", "age": "55-74", "education": "HighSchool", "ethnic": "Caucasian", "gender": "Male"}, "input.keywords": "(waterfront|toured|sites)", "input.images": "https://farm6.staticflickr.com/5250/5356098283_c11d777877_o.jpg", "input.sentences": "we toured the sites and took many photos including this amusement park on the waterfront .", "output.sentences": "So is that city scape!"}