{"annotation_id": "31203", "per_annotation_id": "31203", "id": "31203_0_2", "persona": {"country": "U.S.A", "politics": "Centrist", "tod": "Afternoon", "age": "25-34", "education": "Master", "ethnic": "EastAsian", "gender": "Male"}, "input.keywords": "(restaurant|rainbow|inside)", "input.images": "https://farm5.staticflickr.com/4098/4897007216_d36a7a72f9_o.jpg", "input.sentences": "with much excitement | he went and ate inside this restaurant at the end of the rainbow .", "output.sentences": "The rainbow actually extended to the inside of the restaurant."}