{"annotation_id": "31523", "per_annotation_id": "31523", "id": "31523_0_2", "persona": {"country": "U.S.A", "politics": "Centrist", "tod": "Night", "age": "25-34", "education": "Bachelor", "ethnic": "Ethnic-CentralAsian", "gender": "Male"}, "input.keywords": "(visiting|time|bed)", "input.images": "https://farm1.staticflickr.com/5/10600729_5480168114_o.jpg", "input.sentences": "after visiting for a while | it is time for the baby to go to bed .", "output.sentences": "A crib was empty and waiting for the child in a decorated room."}