{"annotation_id": "31659", "per_annotation_id": "31659", "id": "31659_0_0", "persona": {"country": "U.S.A", "politics": "Centrist", "tod": "Afternoon", "age": "45-54", "education": "Master", "ethnic": "Caucasian", "gender": "Female"}, "input.keywords": "(world|water|traveling)", "input.images": "https://farm1.staticflickr.com/18/23844065_1c77dcbc93_o.jpg", "input.sentences": "[male] 's family loved traveling across the world by water . they loved the ocean .", "output.sentences": "The wife was on a world wide vacation and was enjoying the view from the top of rocks."}