{"annotation_id": "32973", "per_annotation_id": "32973", "id": "32973_0_0", "persona": {"country": "U.S.A", "politics": "Centrist", "tod": "Night", "age": "35-44", "education": "Bachelor", "ethnic": "Caucasian", "gender": "Male"}, "input.keywords": "(visit|grandma|family)", "input.images": "https://farm1.staticflickr.com/8/8810968_def439f70e_o.jpg", "input.sentences": "a family decided to bring their baby to visit grandma for her birthday .", "output.sentences": "The Winston family had two people with the same birthday, Beulla and their newest arrival Mikayla."}