{"annotation_id": "33365", "per_annotation_id": "33365", "id": "33365_1_2", "persona": {"country": "U.S.A", "politics": "RightWing", "tod": "Afternoon", "age": "12-17", "education": "SomeHighSchool,NoDiploma", "ethnic": "SouthAsian", "gender": "Male"}, "input.keywords": "(time|sights|plenty)", "input.images": "https://farm1.staticflickr.com/170/379290334_f3bc7ca080_o.jpg", "input.sentences": "it would take quite some time to get there but there were plenty of great sights along the way .", "output.sentences": "We spent a plenty of time in a sight scene."}