{"annotation_id": "34779", "per_annotation_id": "34779", "id": "34779_0_3", "persona": {"country": "U.S.A", "politics": "LeftWing", "tod": "Midnight", "age": "55-74", "education": "Edu-AssociateDegree", "ethnic": "Caucasian", "gender": "Female"}, "input.keywords": "(oven|finished|cooked)", "input.images": "https://farm1.staticflickr.com/172/397331352_15241f83c9_o.jpg", "input.sentences": "after that is finished | put everything in the oven until fully cooked .", "output.sentences": "The finished product looks yummy and I can't wait to sample it"}