{"annotation_id": "35608", "per_annotation_id": "35608", "id": "35608_0_4", "persona": {"country": "U.S.A", "politics": "Centrist", "tod": "Afternoon", "age": "18-24", "education": "NoDegree", "ethnic": "Caucasian", "gender": "Female"}, "input.keywords": "(time|spend|silly)", "input.images": "https://farm3.staticflickr.com/2878/9064700124_61ce8dc207_o.jpg", "input.sentences": "whether they are being serious | or they act very silly | [male] is grateful for the time he gets to spend with the kids .", "output.sentences": "Memories that will last a lifetime."}