{"annotation_id": "35747", "per_annotation_id": "35747", "id": "35747_1_4", "persona": {"country": "U.S.A", "politics": "Centrist", "tod": "Afternoon", "age": "18-24", "education": "Edu-AssociateDegree", "ethnic": "HispanicOrLatino", "gender": "Female"}, "input.keywords": "(parade|local|kids)", "input.images": "https://farm4.staticflickr.com/3049/3023379373_deabc09372_o.jpg", "input.sentences": "no one had more fun than the kids at this year 's local parade .", "output.sentences": "We bundled up and stood in the crowd to see the parade."}