{"annotation_id": "36208", "per_annotation_id": "36208", "id": "36208_1_3", "persona": {"country": "U.S.A", "politics": "LeftWing", "tod": "Morning", "age": "35-44", "education": "Bachelor", "ethnic": "Caucasian", "gender": "Female"}, "input.keywords": "(shaved|head|confident)", "input.images": "https://farm6.staticflickr.com/5275/5854121500_6f4624a731_o.jpg", "input.sentences": "he was getting use to his shaved head but he was n't confident about it yet .", "output.sentences": "Many family members were there and everyone posed for pictures"}