{"annotation_id": "36370", "per_annotation_id": "36370", "id": "36370_2_2", "persona": {"country": "U.S.A", "politics": "LeftWing", "tod": "Morning", "age": "18-24", "education": "Edu-AssociateDegree", "ethnic": "Caucasian", "gender": "Female"}, "input.keywords": "(leads|korean|flags)", "input.images": "https://farm8.staticflickr.com/7080/7182706439_af72ec5db5_o.jpg", "input.sentences": "the flag corp leads the way with the american and korean flags .", "output.sentences": "She practiced her sword work every day for years."}