{"annotation_id": "37173", "per_annotation_id": "37173", "id": "37173_0_2", "persona": {"country": "U.S.A", "politics": "Centrist", "tod": "Night", "age": "45-54", "education": "Bachelor", "ethnic": "Caucasian", "gender": "Female"}, "input.keywords": "(table|sat|presentations)", "input.images": "https://farm3.staticflickr.com/2271/2083050647_791375f3cc_o.jpg", "input.sentences": "the leaders sat at a table in front of everybody as they gave their presentations .", "output.sentences": "The people giving the presentations sat at a long table in the front of the room."}