{"annotation_id": "38249", "per_annotation_id": "38249", "id": "38249_0_4", "persona": {"country": "U.S.A", "politics": "Centrist", "tod": "Afternoon", "age": "18-24", "education": "NoDegree", "ethnic": "Caucasian", "gender": "Female"}, "input.keywords": "(tour|offices|government)", "input.images": "https://farm8.staticflickr.com/7165/6427014435_9c7b2e0f82_o.jpg", "input.sentences": "after that we took a tour of the government offices .", "output.sentences": "The government office building tour was very interesting."}