{"annotation_id": "39535", "per_annotation_id": "39535", "id": "39535_0_4", "persona": {"country": "U.S.A", "politics": "LeftWing", "tod": "Afternoon", "age": "18-24", "education": "NoDegree", "ethnic": "Caucasian", "gender": "Male"}, "input.keywords": "(watch|pay|eat)", "input.images": "https://farm1.staticflickr.com/33/67777987_42edfbf311_o.jpg", "input.sentences": "and she will eat your doritos if you do n't pay attention so watch out .", "output.sentences": "But like everyone else, he likes to watch TV, play and eat"}