{"annotation_id": "39894", "per_annotation_id": "39894", "id": "39894_1_4", "persona": {"country": "U.S.A", "politics": "LeftWing", "tod": "Morning", "age": "25-34", "education": "Master", "ethnic": "Ethnic-NativeAmerican", "gender": "Male"}, "input.keywords": "(time|missionaries|advice)", "input.images": "https://farm5.staticflickr.com/4054/4309987511_aecce18196_o.jpg", "input.sentences": "other 's had been missionaries for a long time and gave some advice .", "output.sentences": "IT IS A MEETING HALL"}