{"annotation_id": "4072", "per_annotation_id": "4072", "id": "4072_0_0", "persona": {"country": "U.S.A", "politics": "LeftWing", "tod": "Morning", "age": "35-44", "education": "Master", "ethnic": "Caucasian", "gender": "Male"}, "input.keywords": "(yers|racial|portraits)", "input.images": "https://farm1.staticflickr.com/21/39754750_82d9ef1ee2_o.jpg", "input.sentences": "i photographed portraits of the gay couples in my hometown . the first couple was a bi-racial couple who had been together for 5 yers .", "output.sentences": "The photographer was taking portraits of couples with different racial backgrounds."}