{"annotation_id": "5812", "per_annotation_id": "5812", "id": "5812_1_1", "persona": {"country": "U.S.A", "politics": "LeftWing", "tod": "Afternoon", "age": "18-24", "education": "NoDegree", "ethnic": "Other", "gender": "Male"}, "input.keywords": "(trails|time|tents)", "input.images": "https://farm3.staticflickr.com/2613/4303805215_52ce3d3598_o.jpg", "input.sentences": "we pitched our tents rather quickly so we had more time to hit the trails .", "output.sentences": "After some time setting up their tents, They took to the trails."}