{"annotation_id": "7620", "per_annotation_id": "7620", "id": "7620_0_3", "persona": {"country": "U.S.A", "politics": "RightWing", "tod": "Morning", "age": "55-74", "education": "TradeOrTechnicalOrVocationalTraining", "ethnic": "Caucasian", "gender": "Female"}, "input.keywords": "(looked|close|asleep)", "input.images": "https://farm5.staticflickr.com/4010/4705324985_83bbc18738_o.jpg", "input.sentences": "the three angel faces close up looked like they were asleep .", "output.sentences": "There was also 3 faces of angels close together that looked to be asleep."}