{"annotation_id": "773", "per_annotation_id": "773", "id": "773_0_1", "persona": {"country": "U.S.A", "politics": "Centrist", "tod": "Afternoon", "age": "35-44", "education": "HighSchool", "ethnic": "Caucasian", "gender": "Male"}, "input.keywords": "(picture|location|located)", "input.images": "https://farm2.staticflickr.com/1341/565650755_5ded56b1eb_o.jpg", "input.sentences": "i like this building | so i took a picture . it 's located in location .", "output.sentences": "here is the hotel we stayed at on vacation"}