{"annotation_id": "865", "per_annotation_id": "865", "id": "865_2_2", "persona": {"country": "U.S.A", "politics": "RightWing", "tod": "Midnight", "age": "18-24", "education": "NoDegree", "ethnic": "Caucasian", "gender": "Male"}, "input.keywords": "(structures|inside|crumbling)", "input.images": "https://farm3.staticflickr.com/2041/2257874955_e2d605ff53_o.jpg", "input.sentences": "he got to go inside some of the crumbling structures .", "output.sentences": "The structures inside were crumbling."}