{"annotation_id": "95", "per_annotation_id": "95", "id": "95_0_4", "persona": {"country": "U.S.A", "politics": "Centrist", "tod": "Afternoon", "age": "25-34", "education": "TradeOrTechnicalOrVocationalTraining", "ethnic": "Caucasian", "gender": "Female"}, "input.keywords": "(recovered|people|cool)", "input.images": "https://farm2.staticflickr.com/1420/723285536_e4b56d58e7_o.jpg", "input.sentences": "but she recovered her cool as there were many other people in attendance", "output.sentences": "The rehab program BBQ was a success."}