{"annotation_id": "9715", "per_annotation_id": "9715", "id": "9715_0_1", "persona": {"country": "U.S.A", "politics": "LeftWing", "tod": "Afternoon", "age": "45-54", "education": "TradeOrTechnicalOrVocationalTraining", "ethnic": "Caucasian", "gender": "Female"}, "input.keywords": "(workers|rescue|lot)", "input.images": "https://farm9.staticflickr.com/8173/8072225414_2d141490b7_o.jpg", "input.sentences": "there was a lot of rescue workers .", "output.sentences": "A lot of rescue workers from several townships were called in to help."}